atop/__init__.py
atop/atop.py
atop/modules/__init__.py
atop/modules/const.py
atop/modules/telegramhelper.py
atop/modules/util.py
atop-0.2.25.dist-info/LICENSE
atop-0.2.25.dist-info/METADATA
atop-0.2.25.dist-info/WHEEL
atop-0.2.25.dist-info/entry_points.txt
atop-0.2.25.dist-info/top_level.txt
atop-0.2.25.dist-info/RECORD
