Metadata-Version: 2.1
Name: atop
Version: 0.2.25
Summary: "A TON of Privacy" formally called ATOP ... is a tool for conducting OSINT investigations on TON NFTs.
Home-page: https://github.com/aaarghhh/a_TON_of_privacy
Author: Aaarghhh
Author-email: giacomo@udontknow.us
License: MIT
License-File: LICENSE
Requires-Dist: beautifulsoup4 ==4.12.2
Requires-Dist: bitarray ==2.6.0
Requires-Dist: bs4 ==0.0.1
Requires-Dist: build ==1.0.3
Requires-Dist: certifi ==2023.11.17
Requires-Dist: cffi ==1.16.0
Requires-Dist: charset-normalizer ==3.3.2
Requires-Dist: colorama ==0.4.6
Requires-Dist: crc16 ==0.1.1
Requires-Dist: crc32c ==2.4.1
Requires-Dist: idna ==3.6
Requires-Dist: load-dotenv ==0.1.0
Requires-Dist: multidict ==6.0.5
Requires-Dist: numpy ==1.26.3
Requires-Dist: packaging ==23.2
Requires-Dist: pyaes ==1.6.1
Requires-Dist: pyasn1 ==0.5.1
Requires-Dist: pycparser ==2.22
Requires-Dist: pydantic ==1.10.17
Requires-Dist: PyNaCl ==1.5.0
Requires-Dist: pyproject-hooks ==1.0.0
Requires-Dist: PySocks ==1.7.1
Requires-Dist: python-dotenv ==1.0.0
Requires-Dist: pytonlib ==0.0.61
Requires-Dist: requests ==2.31.0
Requires-Dist: rsa ==4.9
Requires-Dist: soupsieve ==2.5
Requires-Dist: Telethon ==1.33.1
Requires-Dist: tonsdk ==1.0.14
Requires-Dist: tvm-valuetypes ==0.0.12
Requires-Dist: typing-extensions ==4.12.2
Requires-Dist: urllib3 ==2.1.0
Requires-Dist: yarl ==1.9.4
